loopimer
