Metadata-Version: 2.1
Name: loopimer
Version: 1.0.2
Summary: Package for time-controlled consecutive execution of a  function using threading.
Home-page: https://github.com/rouzbeh-afrasiabi/loopimer
Author: Rouzbeh Afrasiabi
Author-email: rouzbeh.afrasiabi@gmail.com
License: UNKNOWN
Download-URL: https://github.com/rouzbeh-afrasiabi/loopimer/archive/v.1.0.2.tar.gz
Keywords: time,loop,control,threading,function
Platform: UNKNOWN
Classifier: Programming Language :: Python :: 3.6
Classifier: License :: OSI Approved :: MIT License
Classifier: Operating System :: OS Independent
